clockipy.py
Clockipy-0.0.4.dist-info/METADATA
Clockipy-0.0.4.dist-info/WHEEL
Clockipy-0.0.4.dist-info/entry_points.txt
Clockipy-0.0.4.dist-info/top_level.txt
Clockipy-0.0.4.dist-info/RECORD
