Metadata-Version: 2.1
Name: Clockipy
Version: 0.0.4
Summary: Clokify CLI, Manage Time, Timers
Home-page: https://github.com/null011/ClockiPy
Author: Noe Macias
Author-email: notnull011@gmail.com
License: UNKNOWN
Project-URL: Bug Tracker, https://github.com/null011/ClockiPy/issues
Platform: UNKNOWN
Classifier: Programming Language :: Python :: 3
Classifier: License :: OSI Approved :: MIT License
Classifier: Operating System :: OS Independent
Requires-Python: >=3.6
Requires-Dist: httpx
Requires-Dist: pydantic
Requires-Dist: pytz
Requires-Dist: rich
